ffmpeg_stream_to_numpy/LICENSE
ffmpeg_stream_to_numpy/README.MD
ffmpeg_stream_to_numpy/__init__.py
ffmpeg_stream_to_numpy/requirements.txt
ffmpeg_stream_to_numpy/thirdparty.json
ffmpeg_stream_to_numpy-0.10.dist-info/LICENSE.rst
ffmpeg_stream_to_numpy-0.10.dist-info/METADATA
ffmpeg_stream_to_numpy-0.10.dist-info/WHEEL
ffmpeg_stream_to_numpy-0.10.dist-info/top_level.txt
ffmpeg_stream_to_numpy-0.10.dist-info/RECORD
