Metadata-Version: 2.1
Name: ffmpeg-stream-to-numpy
Version: 0.10
Summary: ffmpeg stream to numpy arrays
Home-page: https://github.com/hansalemaos/ffmpeg_stream_to_numpy
Author: Johannes Fischer
Author-email: <aulasparticularesdealemaosp@gmail.com>
License: MIT
Keywords: ffmpeg,numpy,cv2,video,stream
Classifier: Development Status :: 4 - Beta
Classifier: Programming Language :: Python :: 3 :: Only
Classifier: Programming Language :: Python :: 3.9
Classifier: Topic :: Scientific/Engineering :: Visualization
Classifier: Topic :: Software Development :: Libraries :: Python Modules
Classifier: Topic :: Text Editors :: Text Processing
Classifier: Topic :: Text Processing :: General
Classifier: Topic :: Text Processing :: Indexing
Classifier: Topic :: Text Processing :: Filters
Classifier: Topic :: Utilities
License-File: LICENSE.rst
Requires-Dist: easy-symlink
Requires-Dist: get-video-len
Requires-Dist: numpy
